newline_tools/__init__.py
newline_tools/__main__.py
newline_tools/dedupe.py
newline_tools/sample.py
newline_tools/shuffle.py
newline_tools/split.py
newline_tools/utils.py
newline_tools-0.1.0.dist-info/LICENSE
newline_tools-0.1.0.dist-info/METADATA
newline_tools-0.1.0.dist-info/WHEEL
newline_tools-0.1.0.dist-info/entry_points.txt
newline_tools-0.1.0.dist-info/top_level.txt
newline_tools-0.1.0.dist-info/RECORD
